{
  "schema_version": 1,
  "profile_count": 16,
  "required_global_identity_fields": [
    "peer_operator"
  ],
  "required_attestation_fields": [
    "attesting_organization",
    "attesting_contact",
    "attestation_timestamp",
    "package_team_member=false",
    "repository_fixture_generated=false"
  ],
  "profiles": [
    {
      "profile": "assertion-client",
      "counterpart_id": "assertion-client-harness",
      "runtime_profile": "production",
      "required_targets": [
        "RFC 7515",
        "RFC 7517",
        "RFC 7518",
        "RFC 7519",
        "RFC 7521",
        "RFC 7523",
        "RFC 7009"
      ],
      "scenario_ids": [
        "jwt-client-auth",
        "assertion-grant",
        "jwt-bearer-claim-validation",
        "token-revocation",
        "jwks-key-selection"
      ],
      "required_identity_fields": [
        "peer_name",
        "peer_version"
      ],
      "required_global_identity_fields": [
        "peer_operator"
      ],
      "required_container_fields": [
        "image_ref",
        "image_digest"
      ],
      "expected_execution_style": "black-box-http",
      "required_attestation_fields": [
        "attesting_organization",
        "attesting_contact",
        "attestation_timestamp",
        "package_team_member=false",
        "repository_fixture_generated=false"
      ],
      "required_artifacts": [
        "http-transcript.yaml",
        "jwt-assertions.json",
        "result.yaml"
      ]
    },
    {
      "profile": "browser",
      "counterpart_id": "browser-rp",
      "runtime_profile": "hardening",
      "required_targets": [
        "RFC 6749",
        "RFC 7636",
        "RFC 7516",
        "RFC 8414",
        "RFC 8615",
        "RFC 9207",
        "OIDC Core 1.0",
        "OIDC Discovery 1.0",
        "OIDC UserInfo"
      ],
      "scenario_ids": [
        "browser-authz-code",
        "browser-oidc-discovery",
        "browser-userinfo",
        "browser-jwe-id-token",
        "browser-issuer-parameter",
        "browser-hardening-discovery-truthfulness"
      ],
      "required_identity_fields": [
        "peer_name",
        "peer_version"
      ],
      "required_global_identity_fields": [
        "peer_operator"
      ],
      "required_container_fields": [
        "image_ref",
        "image_digest"
      ],
      "expected_execution_style": "black-box-browser",
      "required_attestation_fields": [
        "attesting_organization",
        "attesting_contact",
        "attestation_timestamp",
        "package_team_member=false",
        "repository_fixture_generated=false"
      ],
      "required_artifacts": [
        "http-transcript.yaml",
        "browser-trace.json",
        "result.yaml"
      ]
    },
    {
      "profile": "client-mgmt",
      "counterpart_id": "client-mgmt-harness",
      "runtime_profile": "hardening",
      "required_targets": [
        "RFC 7591",
        "RFC 7592"
      ],
      "scenario_ids": [
        "client-register",
        "client-read-update-delete",
        "client-registration-access-token"
      ],
      "required_identity_fields": [
        "peer_name",
        "peer_version"
      ],
      "required_global_identity_fields": [
        "peer_operator"
      ],
      "required_container_fields": [
        "image_ref",
        "image_digest"
      ],
      "expected_execution_style": "black-box-http",
      "required_attestation_fields": [
        "attesting_organization",
        "attesting_contact",
        "attestation_timestamp",
        "package_team_member=false",
        "repository_fixture_generated=false"
      ],
      "required_artifacts": [
        "http-transcript.yaml",
        "client-metadata.json",
        "result.yaml"
      ]
    },
    {
      "profile": "device",
      "counterpart_id": "device-client",
      "runtime_profile": "hardening",
      "required_targets": [
        "RFC 8628"
      ],
      "scenario_ids": [
        "device-authorization",
        "device-token-poll",
        "device-slow-down",
        "device-denial-replay"
      ],
      "required_identity_fields": [
        "peer_name",
        "peer_version"
      ],
      "required_global_identity_fields": [
        "peer_operator"
      ],
      "required_container_fields": [
        "image_ref",
        "image_digest"
      ],
      "expected_execution_style": "black-box-cli",
      "required_attestation_fields": [
        "attesting_organization",
        "attesting_contact",
        "attestation_timestamp",
        "package_team_member=false",
        "repository_fixture_generated=false"
      ],
      "required_artifacts": [
        "http-transcript.yaml",
        "stdout.log",
        "result.yaml"
      ]
    },
    {
      "profile": "dpop",
      "counterpart_id": "dpop-client",
      "runtime_profile": "hardening",
      "required_targets": [
        "RFC 9449",
        "RFC 9700"
      ],
      "scenario_ids": [
        "dpop-token",
        "dpop-replay-rejection",
        "dpop-nonce-recovery"
      ],
      "required_identity_fields": [
        "peer_name",
        "peer_version"
      ],
      "required_global_identity_fields": [
        "peer_operator"
      ],
      "required_container_fields": [
        "image_ref",
        "image_digest"
      ],
      "expected_execution_style": "black-box-http",
      "required_attestation_fields": [
        "attesting_organization",
        "attesting_contact",
        "attestation_timestamp",
        "package_team_member=false",
        "repository_fixture_generated=false"
      ],
      "required_artifacts": [
        "http-transcript.yaml",
        "proof-jwts.json",
        "result.yaml"
      ]
    },
    {
      "profile": "gateway",
      "counterpart_id": "gateway-peer",
      "runtime_profile": "hardening",
      "required_targets": [
        "RFC 6750",
        "RFC 8414",
        "RFC 8615",
        "RFC 7517",
        "RFC 9700",
        "RFC 9728",
        "OIDC Discovery 1.0"
      ],
      "scenario_ids": [
        "gateway-discovery",
        "gateway-jwks",
        "gateway-protected-resource",
        "gateway-hardening-discovery-truthfulness"
      ],
      "required_identity_fields": [
        "peer_name",
        "peer_version"
      ],
      "required_global_identity_fields": [
        "peer_operator"
      ],
      "required_container_fields": [
        "image_ref",
        "image_digest"
      ],
      "expected_execution_style": "black-box-http",
      "required_attestation_fields": [
        "attesting_organization",
        "attesting_contact",
        "attestation_timestamp",
        "package_team_member=false",
        "repository_fixture_generated=false"
      ],
      "required_artifacts": [
        "http-transcript.yaml",
        "gateway-config.yaml",
        "result.yaml"
      ]
    },
    {
      "profile": "mtls",
      "counterpart_id": "mtls-peer",
      "runtime_profile": "hardening",
      "required_targets": [
        "RFC 8705",
        "RFC 9700"
      ],
      "scenario_ids": [
        "mtls-token",
        "mtls-bound-resource",
        "mtls-token-exchange"
      ],
      "required_identity_fields": [
        "peer_name",
        "peer_version"
      ],
      "required_global_identity_fields": [
        "peer_operator"
      ],
      "required_container_fields": [
        "image_ref",
        "image_digest"
      ],
      "expected_execution_style": "black-box-http-mtls",
      "required_attestation_fields": [
        "attesting_organization",
        "attesting_contact",
        "attestation_timestamp",
        "package_team_member=false",
        "repository_fixture_generated=false"
      ],
      "required_artifacts": [
        "http-transcript.yaml",
        "certificate-chain.pem",
        "result.yaml"
      ]
    },
    {
      "profile": "native",
      "counterpart_id": "native-client",
      "runtime_profile": "hardening",
      "required_targets": [
        "RFC 7636",
        "RFC 8252",
        "RFC 7516",
        "RFC 9207"
      ],
      "scenario_ids": [
        "native-loopback",
        "native-custom-scheme",
        "native-jwe-id-token",
        "native-issuer-parameter"
      ],
      "required_identity_fields": [
        "peer_name",
        "peer_version"
      ],
      "required_global_identity_fields": [
        "peer_operator"
      ],
      "required_container_fields": [
        "image_ref",
        "image_digest"
      ],
      "expected_execution_style": "black-box-cli",
      "required_attestation_fields": [
        "attesting_organization",
        "attesting_contact",
        "attestation_timestamp",
        "package_team_member=false",
        "repository_fixture_generated=false"
      ],
      "required_artifacts": [
        "http-transcript.yaml",
        "stdout.log",
        "result.yaml"
      ]
    },
    {
      "profile": "ops-cli",
      "counterpart_id": "ops-cli-harness",
      "runtime_profile": "production",
      "required_targets": [
        "OpenAPI 3.1 / 3.2 compatible public contract",
        "OpenRPC 1.4.x admin/control-plane contract",
        "CLI operator surface",
        "Bootstrap and migration lifecycle",
        "Key lifecycle and JWKS publication",
        "Import/export portability",
        "Release bundle and signature verification"
      ],
      "scenario_ids": [
        "cli-surface",
        "bootstrap-migration",
        "release-bundle-signing",
        "contract-export-verify",
        "operator-lifecycle-roundtrip"
      ],
      "required_identity_fields": [
        "peer_name",
        "peer_version"
      ],
      "required_global_identity_fields": [
        "peer_operator"
      ],
      "required_container_fields": [
        "image_ref",
        "image_digest"
      ],
      "expected_execution_style": "black-box-cli",
      "required_attestation_fields": [
        "attesting_organization",
        "attesting_contact",
        "attestation_timestamp",
        "package_team_member=false",
        "repository_fixture_generated=false"
      ],
      "required_artifacts": [
        "stdout.log",
        "result.yaml"
      ]
    },
    {
      "profile": "par-jar-rar",
      "counterpart_id": "par-jar-rar-client",
      "runtime_profile": "hardening",
      "required_targets": [
        "RFC 9101",
        "RFC 9126",
        "RFC 9396",
        "RFC 8707"
      ],
      "scenario_ids": [
        "par-submit",
        "jar-authorize",
        "rar-authorize",
        "rar-resource-binding"
      ],
      "required_identity_fields": [
        "peer_name",
        "peer_version"
      ],
      "required_global_identity_fields": [
        "peer_operator"
      ],
      "required_container_fields": [
        "image_ref",
        "image_digest"
      ],
      "expected_execution_style": "black-box-http",
      "required_attestation_fields": [
        "attesting_organization",
        "attesting_contact",
        "attestation_timestamp",
        "package_team_member=false",
        "repository_fixture_generated=false"
      ],
      "required_artifacts": [
        "http-transcript.yaml",
        "request-objects/",
        "result.yaml"
      ]
    },
    {
      "profile": "resource-server",
      "counterpart_id": "resource-server",
      "runtime_profile": "hardening",
      "required_targets": [
        "RFC 6750",
        "RFC 7662",
        "RFC 8693",
        "RFC 8707",
        "RFC 9068",
        "RFC 9728",
        "RFC 9700"
      ],
      "scenario_ids": [
        "bearer-resource",
        "introspection-resource",
        "jwt-access-token-resource",
        "token-exchange-resource",
        "resource-indicator-binding",
        "hardening-protected-resource-metadata"
      ],
      "required_identity_fields": [
        "peer_name",
        "peer_version"
      ],
      "required_global_identity_fields": [
        "peer_operator"
      ],
      "required_container_fields": [
        "image_ref",
        "image_digest"
      ],
      "expected_execution_style": "black-box-http",
      "required_attestation_fields": [
        "attesting_organization",
        "attesting_contact",
        "attestation_timestamp",
        "package_team_member=false",
        "repository_fixture_generated=false"
      ],
      "required_artifacts": [
        "http-transcript.yaml",
        "resource-response.log",
        "result.yaml"
      ]
    },
    {
      "profile": "rp-session-logout",
      "counterpart_id": "rp-session-logout-rp",
      "runtime_profile": "hardening",
      "required_targets": [
        "RFC 6265",
        "OIDC Session Management",
        "OIDC RP-Initiated Logout",
        "OIDC Front-Channel Logout",
        "OIDC Back-Channel Logout"
      ],
      "scenario_ids": [
        "session-state-check",
        "rp-initiated-logout",
        "frontchannel-fanout",
        "backchannel-delivery",
        "cookie-rotation-and-replay"
      ],
      "required_identity_fields": [
        "peer_name",
        "peer_version"
      ],
      "required_global_identity_fields": [
        "peer_operator"
      ],
      "required_container_fields": [
        "image_ref",
        "image_digest"
      ],
      "expected_execution_style": "black-box-browser",
      "required_attestation_fields": [
        "attesting_organization",
        "attesting_contact",
        "attestation_timestamp",
        "package_team_member=false",
        "repository_fixture_generated=false"
      ],
      "required_artifacts": [
        "http-transcript.yaml",
        "browser-trace.json",
        "logout-tokens.json",
        "result.yaml"
      ]
    },
    {
      "profile": "runner-hypercorn",
      "counterpart_id": "hypercorn-runner",
      "runtime_profile": "production",
      "required_targets": [
        "ASGI 3 application package",
        "Runner profile: Hypercorn"
      ],
      "scenario_ids": [
        "runner-launch",
        "runner-health",
        "runner-contract-hash"
      ],
      "required_identity_fields": [
        "peer_name",
        "peer_version"
      ],
      "required_global_identity_fields": [
        "peer_operator"
      ],
      "required_container_fields": [
        "image_ref",
        "image_digest"
      ],
      "expected_execution_style": "black-box-http",
      "required_attestation_fields": [
        "attesting_organization",
        "attesting_contact",
        "attestation_timestamp",
        "package_team_member=false",
        "repository_fixture_generated=false"
      ],
      "required_artifacts": [
        "http-transcript.yaml",
        "result.yaml"
      ]
    },
    {
      "profile": "runner-tigrcorn",
      "counterpart_id": "tigrcorn-runner",
      "runtime_profile": "production",
      "required_targets": [
        "ASGI 3 application package",
        "Runner profile: Tigrcorn"
      ],
      "scenario_ids": [
        "runner-launch",
        "runner-health",
        "runner-contract-hash"
      ],
      "required_identity_fields": [
        "peer_name",
        "peer_version"
      ],
      "required_global_identity_fields": [
        "peer_operator"
      ],
      "required_container_fields": [
        "image_ref",
        "image_digest"
      ],
      "expected_execution_style": "black-box-http",
      "required_attestation_fields": [
        "attesting_organization",
        "attesting_contact",
        "attestation_timestamp",
        "package_team_member=false",
        "repository_fixture_generated=false"
      ],
      "required_artifacts": [
        "http-transcript.yaml",
        "result.yaml"
      ]
    },
    {
      "profile": "runner-uvicorn",
      "counterpart_id": "uvicorn-runner",
      "runtime_profile": "production",
      "required_targets": [
        "ASGI 3 application package",
        "Runner profile: Uvicorn"
      ],
      "scenario_ids": [
        "runner-launch",
        "runner-health",
        "runner-contract-hash"
      ],
      "required_identity_fields": [
        "peer_name",
        "peer_version"
      ],
      "required_global_identity_fields": [
        "peer_operator"
      ],
      "required_container_fields": [
        "image_ref",
        "image_digest"
      ],
      "expected_execution_style": "black-box-http",
      "required_attestation_fields": [
        "attesting_organization",
        "attesting_contact",
        "attestation_timestamp",
        "package_team_member=false",
        "repository_fixture_generated=false"
      ],
      "required_artifacts": [
        "http-transcript.yaml",
        "result.yaml"
      ]
    },
    {
      "profile": "spa",
      "counterpart_id": "spa-rp",
      "runtime_profile": "hardening",
      "required_targets": [
        "RFC 6749",
        "RFC 7636",
        "OIDC Core 1.0",
        "OIDC Discovery 1.0"
      ],
      "scenario_ids": [
        "spa-authz-code-pkce",
        "spa-discovery",
        "spa-hardening-discovery-truthfulness"
      ],
      "required_identity_fields": [
        "peer_name",
        "peer_version"
      ],
      "required_global_identity_fields": [
        "peer_operator"
      ],
      "required_container_fields": [
        "image_ref",
        "image_digest"
      ],
      "expected_execution_style": "black-box-browser",
      "required_attestation_fields": [
        "attesting_organization",
        "attesting_contact",
        "attestation_timestamp",
        "package_team_member=false",
        "repository_fixture_generated=false"
      ],
      "required_artifacts": [
        "http-transcript.yaml",
        "browser-trace.json",
        "result.yaml"
      ]
    }
  ]
}
